LICENSE.txt
pcpp/__init__.py
pcpp/evaluator.py
pcpp/lextab.py
pcpp/parser.py
pcpp/parsetab.py
pcpp/pcmd.py
pcpp/preprocessor.py
pcpp/ply/ply/__init__.py
pcpp/ply/ply/cpp.py
pcpp/ply/ply/ctokens.py
pcpp/ply/ply/lex.py
pcpp/ply/ply/yacc.py
pcpp/ply/ply/ygen.py
pcpp-1.30.dist-info/LICENSE.txt
pcpp-1.30.dist-info/METADATA
pcpp-1.30.dist-info/WHEEL
pcpp-1.30.dist-info/entry_points.txt
pcpp-1.30.dist-info/top_level.txt
pcpp-1.30.dist-info/RECORD
