Metadata-Version: 1.1
Name: pcpp
Version: 1.30
Summary: A C99 preprocessor written in pure Python
Home-page: https://github.com/ned14/pcpp
Author: Niall Douglas and David Beazley
Author-email: UNKNOWN
License: BSD
Platform: UNKNOWN
Classifier: Development Status :: 5 - Production/Stable
Classifier: Intended Audience :: Developers
Classifier: Topic :: Software Development :: Build Tools
Classifier: License :: OSI Approved :: BSD License
Classifier: Programming Language :: Python :: 2
Classifier: Programming Language :: Python :: 2.7
Classifier: Programming Language :: Python :: 3
